gen_epix/__init__.py
gen_epix/casedb/__init__.py
gen_epix/casedb/app.py
gen_epix/casedb/app_setup.py
gen_epix/casedb/env.py
gen_epix/casedb/api/__init__.py
gen_epix/casedb/api/abac.py
gen_epix/casedb/api/case.py
gen_epix/casedb/api/geo.py
gen_epix/casedb/api/ontology.py
gen_epix/casedb/api/organization.py
gen_epix/casedb/api/router.py
gen_epix/casedb/api/subject.py
gen_epix/casedb/config/__init__.py
gen_epix/casedb/domain/__init__.py
gen_epix/casedb/domain/enum.py
gen_epix/casedb/domain/exc.py
gen_epix/casedb/domain/command/__init__.py
gen_epix/casedb/domain/command/abac.py
gen_epix/casedb/domain/command/case.py
gen_epix/casedb/domain/command/geo.py
gen_epix/casedb/domain/command/ontology.py
gen_epix/casedb/domain/command/organization.py
gen_epix/casedb/domain/command/seqdb.py
gen_epix/casedb/domain/command/subject.py
gen_epix/casedb/domain/model/__init__.py
gen_epix/casedb/domain/model/geo.py
gen_epix/casedb/domain/model/ontology.py
gen_epix/casedb/domain/model/organization.py
gen_epix/casedb/domain/model/seqdb.py
gen_epix/casedb/domain/model/subject.py
gen_epix/casedb/domain/model/abac/__init__.py
gen_epix/casedb/domain/model/abac/policy.py
gen_epix/casedb/domain/model/abac/rights.py
gen_epix/casedb/domain/model/case/__init__.py
gen_epix/casedb/domain/model/case/case.py
gen_epix/casedb/domain/model/case/complete_case_type.py
gen_epix/casedb/domain/policy/__init__.py
gen_epix/casedb/domain/policy/abac.py
gen_epix/casedb/domain/policy/permission.py
gen_epix/casedb/domain/repository/__init__.py
gen_epix/casedb/domain/repository/case.py
gen_epix/casedb/domain/repository/geo.py
gen_epix/casedb/domain/repository/ontology.py
gen_epix/casedb/domain/repository/organization.py
gen_epix/casedb/domain/repository/subject.py
gen_epix/casedb/domain/repository/system.py
gen_epix/casedb/domain/service/__init__.py
gen_epix/casedb/domain/service/abac.py
gen_epix/casedb/domain/service/case.py
gen_epix/casedb/domain/service/geo.py
gen_epix/casedb/domain/service/ontology.py
gen_epix-6.1.0.dist-info/licenses/LICENSE
gen_epix-6.1.0.dist-info/METADATA
gen_epix-6.1.0.dist-info/WHEEL
gen_epix-6.1.0.dist-info/top_level.txt
gen_epix-6.1.0.dist-info/RECORD
