Metadata-Version: 2.4
Name: Gen-EpiX
Version: 6.1.0
Summary: Genomic Epidemiology platform for disease X
Author-email: RIVM-bioinformatics <ids-bioinformatics@rivm.nl>
License-Expression: EUPL-1.2
Project-URL: Homepage, https://github.com/RIVM-bioinformatics/gen-epix-api/
Project-URL: Documentation, https://rivm-bioinformatics.github.io/gen-epix-api/
Keywords: Genomic Epidemiology,Disease X,Bioinformatics
Classifier: Programming Language :: Python :: 3.13
Classifier: Operating System :: OS Independent
Classifier: Development Status :: 4 - Beta
Classifier: Intended Audience :: Developers
Classifier: Intended Audience :: Science/Research
Classifier: Topic :: Scientific/Engineering :: Bio-Informatics
Requires-Python: >=3.13
License-File: LICENSE
Requires-Dist: fastapi[standard]==0.116.2
Requires-Dist: gunicorn==23.0.*
Requires-Dist: starlette==0.47.3
Requires-Dist: httpx==0.28.1
Requires-Dist: python-jose==3.5.0
Requires-Dist: sqlalchemy==2.0.43
Requires-Dist: sqlalchemy_utils==0.42.0
Requires-Dist: pydantic==2.11.7
Requires-Dist: ulid-py==1.1.0
Requires-Dist: fire==0.7.1
Requires-Dist: dynaconf==3.2.11
Requires-Dist: PyYAML==6.0.2
Requires-Dist: scipy==1.16.2
Requires-Dist: numpy==2.3.3
Requires-Dist: biopython==1.85
Requires-Dist: cachetools==5.5.2
Requires-Dist: slowapi==0.1.9
Provides-Extra: dependencies
Requires-Dist: pytest; extra == "dependencies"
Requires-Dist: pytest-cov; extra == "dependencies"
Requires-Dist: pytest-mock; extra == "dependencies"
Requires-Dist: pytest-dependency; extra == "dependencies"
Requires-Dist: pyinstrument; extra == "dependencies"
Requires-Dist: isort; extra == "dependencies"
Requires-Dist: black; extra == "dependencies"
Requires-Dist: pylint; extra == "dependencies"
Requires-Dist: mypy; extra == "dependencies"
Requires-Dist: cryptography; extra == "dependencies"
Requires-Dist: pandas-stubs; extra == "dependencies"
Requires-Dist: openpyxl; extra == "dependencies"
Requires-Dist: types-cachetools; extra == "dependencies"
Requires-Dist: types-python-jose; extra == "dependencies"
Dynamic: license-file
